bat/__init__.py
bat/agent/__init__.py
bat/agent/_executor.py
bat/agent/application.py
bat/agent/config.py
bat/agent/graph.py
bat/agent/state.py
bat/chat_model_client/__init__.py
bat/chat_model_client/client.py
bat/chat_model_client/config.py
bat/logging/__init__.py
bat/logging/logging.py
bat/prebuilt/__init__.py
bat/prebuilt/call_agent_node.py
bat/prebuilt/prebuilt_workflow.py
bat/prebuilt/react_loop.py
bat_adk-2025.12.dist-info/METADATA
bat_adk-2025.12.dist-info/WHEEL
bat_adk-2025.12.dist-info/top_level.txt
bat_adk-2025.12.dist-info/RECORD
