Metadata-Version: 2.4
Name: bat-adk
Version: 2025.12
Summary: Software Development Kit for building AI Agents in BubbleRAN MX-PDK and MX-AI
Author-email: Andrea LEONE <andrea.leone@bubbleran.com>
Project-URL: Homepage, https://bubbleran.com/
Project-URL: Repository, https://github.com/bubbleran/bat
Classifier: Programming Language :: Python :: 3
Classifier: Operating System :: OS Independent
Requires-Python: >=3.12
Requires-Dist: a2a-sdk>=0.3.20
Requires-Dist: a2a-sdk[http-server]
Requires-Dist: httpx>=0.28.1
Requires-Dist: langchain>=0.3.24
Requires-Dist: langchain-mcp-adapters<0.2.0,>=0.1.13
Requires-Dist: langchain-nvidia-ai-endpoints>=0.3.9
Requires-Dist: langchain-openai>=0.3.14
Requires-Dist: langchain-ollama>=0.3.3
Requires-Dist: langgraph>=1.0.0
Requires-Dist: mcp[cli]>=1.17.0
Requires-Dist: pydantic>=2.10.6
Requires-Dist: pyyaml>=6.0.1
Requires-Dist: uvicorn>=0.37.0
